{
  "README.md": {
    "scroll": 19.25155925155925,
    "cursor": {
      "from": {
        "line": 0,
        "ch": 0
      },
      "to": {
        "line": 0,
        "ch": 0
      }
    },
    "expandedKeys": [
      "item-1-0"
    ]
  },
  "content/page/about/index.zh-cn.md": {
    "scroll": 16.702327096424376,
    "cursor": {
      "from": {
        "line": 19,
        "ch": 0
      },
      "to": {
        "line": 19,
        "ch": 0
      }
    },
    "expandedKeys": []
  },
  "content/post/test.md": {
    "scroll": 18.283060071172425,
    "cursor": {
      "from": {
        "line": 12,
        "ch": 4
      },
      "to": {
        "line": 12,
        "ch": 4
      }
    },
    "expandedKeys": []
  },
  "content/page/search/index.md": {
    "scroll": 0,
    "cursor": {
      "from": {
        "line": 0,
        "ch": 0
      },
      "to": {
        "line": 0,
        "ch": 0
      }
    },
    "expandedKeys": []
  },
  "content/page/links/index.md": {
    "scroll": 0,
    "cursor": {
      "from": {
        "line": 0,
        "ch": 0
      },
      "to": {
        "line": 0,
        "ch": 0
      }
    },
    "expandedKeys": []
  },
  "content/page/archives/index.md": {
    "scroll": 0,
    "cursor": {
      "from": {
        "line": 0,
        "ch": 0
      },
      "to": {
        "line": 0,
        "ch": 0
      }
    },
    "expandedKeys": []
  }
}